littlecms/__init__.py
littlecms/_littlecms.cp35-win_amd64.pyd
littlecms/littlecms.py
littlecms/tests/__init__.py
littlecms/tests/n-colour-profile.py
littlecms/tests/n_colour_profile.py
littlecms/tests/reduce_profile_size.py
littlecms/tests/test_all.py
littlecms-0.1b1.dist-info/DESCRIPTION.rst
littlecms-0.1b1.dist-info/METADATA
littlecms-0.1b1.dist-info/RECORD
littlecms-0.1b1.dist-info/WHEEL
littlecms-0.1b1.dist-info/metadata.json
littlecms-0.1b1.dist-info/top_level.txt
