Metadata-Version: 2.0
Name: littlecms
Version: 0.1b1
Summary: Bindings for Little CMS
Home-page: https://johnpfjefferies@bitbucket.org/johnpfjefferies/little-cms-python-bindings
Author: John Jefferies
Author-email: j.jefferies@ntlworld.com
License: BSD
Keywords: LitleCMS,LCMS,ICC,Colour
Platform: UNKNOWN
Classifier: Development Status :: 4 - Beta
Classifier: Intended Audience :: Developers
Classifier: Topic :: Scientific/Engineering :: Visualization
Classifier: License :: OSI Approved :: BSD License
Classifier: Programming Language :: Python :: 3
